DrissionPage_expend/__init__.py
DrissionPage_expend/xhr_request.py
drissionpage_expend-1.0.1.dist-info/licenses/LICENSE
drissionpage_expend-1.0.1.dist-info/METADATA
drissionpage_expend-1.0.1.dist-info/WHEEL
drissionpage_expend-1.0.1.dist-info/top_level.txt
drissionpage_expend-1.0.1.dist-info/RECORD
