Metadata-Version: 2.4
Name: DrissionPage-expend
Version: 1.0.1
Summary: DrissionPage XHR请求扩展库，支持多种数据类型和请求方式
Home-page: https://github.com/your-username/DrissionPage-expend
Author: DrissionPage Community
Author-email: 
Maintainer: DrissionPage Community
License: MIT
Project-URL: Homepage, https://github.com/your-username/DrissionPage-expend
Project-URL: Documentation, https://github.com/your-username/DrissionPage-expend/blob/main/XHR_REQUEST_README.md
Project-URL: Repository, https://github.com/your-username/DrissionPage-expend
Project-URL: Bug Tracker, https://github.com/your-username/DrissionPage-expend/issues
Keywords: drissionpage,xhr,request,http,automation,web-scraping
Classifier: Development Status :: 4 - Beta
Classifier: Intended Audience :: Developers
Classifier: License :: OSI Approved :: MIT License
Classifier: Operating System :: OS Independent
Classifier: Programming Language :: Python :: 3
Classifier: Programming Language :: Python :: 3.7
Classifier: Programming Language :: Python :: 3.8
Classifier: Programming Language :: Python :: 3.9
Classifier: Programming Language :: Python :: 3.10
Classifier: Programming Language :: Python :: 3.11
Classifier: Programming Language :: Python :: 3.12
Classifier: Topic :: Internet :: WWW/HTTP
Classifier: Topic :: Software Development :: Libraries :: Python Modules
Classifier: Topic :: Software Development :: Testing
Requires-Python: >=3.7
License-File: LICENSE
Requires-Dist: DrissionPage>=3.0.0
Provides-Extra: dev
Requires-Dist: pytest>=6.0; extra == "dev"
Requires-Dist: pytest-cov; extra == "dev"
Requires-Dist: black; extra == "dev"
Requires-Dist: flake8; extra == "dev"
Dynamic: home-page
Dynamic: license-file
Dynamic: requires-python
